webapp2_restful/__init__.py
webapp2_restful/routes.py
webapp2_restful-0.1.1.dist-info/DESCRIPTION.rst
webapp2_restful-0.1.1.dist-info/METADATA
webapp2_restful-0.1.1.dist-info/metadata.json
webapp2_restful-0.1.1.dist-info/pbr.json
webapp2_restful-0.1.1.dist-info/RECORD
webapp2_restful-0.1.1.dist-info/top_level.txt
webapp2_restful-0.1.1.dist-info/WHEEL
