Metadata-Version: 2.0
Name: webapp2-restful
Version: 0.1.1
Summary: A Request parsing interface designed to provide simple and uniform access to any variable on the webapp2.Request object in Webapp2
Home-page: https://github.com/ekampf/webapp2_restful
Author: Eran Kampf
Author-email: eran@ekampf.com
License: BSD
Keywords: webapp2_restful
Platform: UNKNOWN
Classifier: Development Status :: 2 - Pre-Alpha
Classifier: Intended Audience :: Developers
Classifier: License :: OSI Approved :: BSD License
Classifier: Natural Language :: English
Classifier: Programming Language :: Python :: 2
Classifier: Programming Language :: Python :: 2.7
Requires-Dist: webapp2 (==2.5.2)
Requires-Dist: webob (==1.2.3)
Requires-Dist: jsonschema (==2.3.0)
Requires-Dist: inflection (==0.3.1)
